{
  "strategy_name": "NFI5MOHO_WIP",
  "params": {
    "max_open_trades": {
      "max_open_trades": 4
    },
    "buy": {
      "buy_dip_threshold_1": 0.02,
      "buy_dip_threshold_10": 0.24,
      "buy_dip_threshold_11": 0.42,
      "buy_dip_threshold_12": 0.66,
      "buy_dip_threshold_2": 0.14,
      "buy_dip_threshold_3": 0.32,
      "buy_dip_threshold_4": 0.5,
      "buy_dip_threshold_5": 0.015,
      "buy_dip_threshold_6": 0.06,
      "buy_dip_threshold_7": 0.24,
      "buy_dip_threshold_8": 0.4,
      "buy_dip_threshold_9": 0.026,
      "buy_ema_rel_15": 0.993,
      "buy_ema_rel_3": 0.981,
      "buy_ema_rel_5": 0.972,
      "buy_ema_rel_7": 0.996,
      "buy_ewo_12": 2.0,
      "buy_ewo_13": -10.4,
      "buy_ewo_16": 2.8,
      "buy_ewo_17": -12.0,
      "buy_pump_pull_threshold_1": 1.75,
      "buy_pump_pull_threshold_2": 1.75,
      "buy_pump_pull_threshold_3": 1.75,
      "buy_pump_pull_threshold_4": 2.2,
      "buy_pump_pull_threshold_5": 2.0,
      "buy_pump_pull_threshold_6": 2.0,
      "buy_pump_pull_threshold_7": 1.7,
      "buy_pump_pull_threshold_8": 1.7,
      "buy_pump_pull_threshold_9": 1.4,
      "buy_pump_threshold_1": 0.5,
      "buy_pump_threshold_2": 0.56,
      "buy_pump_threshold_3": 0.85,
      "buy_pump_threshold_4": 0.4,
      "buy_pump_threshold_5": 0.56,
      "buy_pump_threshold_6": 0.68,
      "buy_pump_threshold_7": 0.66,
      "buy_pump_threshold_8": 0.7,
      "buy_pump_threshold_9": 1.3,
      "low_offset_ema": 0.929,
      "low_offset_kama": 0.972,
      "low_offset_sma": 0.955,
      "low_offset_t3": 0.975,
      "low_offset_trima": 0.949,
      "base_nb_candles_buy": 35,
      "buy_bb20_close_bblowerband_4": 0.973,
      "buy_bb20_volume_4": 10.05,
      "buy_bb40_bbdelta_close_3": 0.048,
      "buy_bb40_closedelta_close_3": 0.013,
      "buy_bb40_tail_bbdelta_3": 0.19,
      "buy_bb_offset_10": 0.987,
      "buy_bb_offset_14": 0.998,
      "buy_bb_offset_18": 0.99,
      "buy_bb_offset_2": 0.988,
      "buy_bb_offset_5": 0.993,
      "buy_bb_offset_6": 0.996,
      "buy_bb_offset_9": 0.984,
      "buy_chop_min_19": 29.8,
      "buy_condition_10_enable": true,
      "buy_condition_11_enable": true,
      "buy_condition_12_enable": true,
      "buy_condition_13_enable": true,
      "buy_condition_14_enable": true,
      "buy_condition_15_enable": true,
      "buy_condition_16_enable": false,
      "buy_condition_17_enable": true,
      "buy_condition_18_enable": true,
      "buy_condition_19_enable": false,
      "buy_condition_1_enable": false,
      "buy_condition_20_enable": true,
      "buy_condition_21_enable": true,
      "buy_condition_2_enable": false,
      "buy_condition_3_enable": false,
      "buy_condition_4_enable": true,
      "buy_condition_5_enable": true,
      "buy_condition_6_enable": true,
      "buy_condition_7_enable": true,
      "buy_condition_8_enable": true,
      "buy_condition_9_enable": true,
      "buy_ema_open_mult_14": 0.011,
      "buy_ema_open_mult_15": 0.02,
      "buy_ema_open_mult_5": 0.025,
      "buy_ema_open_mult_6": 0.024,
      "buy_ema_open_mult_7": 0.021,
      "buy_ma_offset_10": 0.949,
      "buy_ma_offset_11": 0.979,
      "buy_ma_offset_12": 0.956,
      "buy_ma_offset_13": 0.978,
      "buy_ma_offset_14": 0.98,
      "buy_ma_offset_15": 0.985,
      "buy_ma_offset_16": 0.967,
      "buy_ma_offset_17": 0.945,
      "buy_ma_offset_9": 0.982,
      "buy_mfi_1": 21.5,
      "buy_mfi_11": 54.1,
      "buy_mfi_2": 45.7,
      "buy_mfi_9": 56.6,
      "buy_min_inc_1": 0.045,
      "buy_min_inc_11": 0.015,
      "buy_rsi_1": 28.4,
      "buy_rsi_11": 40.3,
      "buy_rsi_12": 39.9,
      "buy_rsi_15": 49.8,
      "buy_rsi_16": 46.1,
      "buy_rsi_18": 24.4,
      "buy_rsi_1h_10": 35.4,
      "buy_rsi_1h_20": 27.4,
      "buy_rsi_1h_21": 38.9,
      "buy_rsi_1h_diff_2": 36.1,
      "buy_rsi_1h_max_1": 78.7,
      "buy_rsi_1h_max_11": 72.4,
      "buy_rsi_1h_max_2": 80.1,
      "buy_rsi_1h_max_9": 76.3,
      "buy_rsi_1h_min_1": 25.2,
      "buy_rsi_1h_min_11": 50.4,
      "buy_rsi_1h_min_19": 48.9,
      "buy_rsi_1h_min_2": 38.9,
      "buy_rsi_1h_min_9": 30.8,
      "buy_rsi_20": 35.5,
      "buy_rsi_21": 18.4,
      "buy_rsi_7": 32.3,
      "buy_rsi_8": 39.7,
      "buy_tail_diff_8": 3.0,
      "buy_volume_10": 1.7,
      "buy_volume_12": 1.8,
      "buy_volume_13": 8.2,
      "buy_volume_14": 7.3,
      "buy_volume_15": 9.6,
      "buy_volume_16": 7.1,
      "buy_volume_17": 5.2,
      "buy_volume_18": 3.5,
      "buy_volume_2": 4.5,
      "buy_volume_20": 5.1,
      "buy_volume_21": 4.9,
      "buy_volume_7": 6.3,
      "buy_volume_8": 5.5,
      "buy_volume_9": 1.56,
      "ewo_high": 7.892,
      "ewo_low": -19.964,
      "fast_ewo": 45,
      "look_back": 11,
      "slow_ewo": 100,
      "spike_threshold": 0.074
    },
    "sell": {
      "high_offset_ema": 1.047,
      "high_offset_kama": 1.07,
      "high_offset_sma": 1.051,
      "high_offset_t3": 0.999,
      "high_offset_trima": 1.096,
      "base_nb_candles_sell": 61,
      "sell_bb_relative_8": 1.209,
      "sell_condition_1_enable": false,
      "sell_condition_2_enable": true,
      "sell_condition_3_enable": true,
      "sell_condition_4_enable": true,
      "sell_condition_5_enable": true,
      "sell_condition_6_enable": true,
      "sell_condition_7_enable": true,
      "sell_condition_8_enable": false,
      "sell_custom_dec_profit_1": 0.019,
      "sell_custom_dec_profit_2": 0.148,
      "sell_custom_profit_0": 0.037,
      "sell_custom_profit_1": 0.1,
      "sell_custom_profit_2": 0.087,
      "sell_custom_profit_3": 0.078,
      "sell_custom_profit_4": 0.506,
      "sell_custom_profit_under_rel_1": 0.014,
      "sell_custom_profit_under_rsi_diff_1": 18.909,
      "sell_custom_rsi_0": 35.504,
      "sell_custom_rsi_1": 33.13,
      "sell_custom_rsi_2": 37.37,
      "sell_custom_rsi_3": 42.27,
      "sell_custom_rsi_4": 57.82,
      "sell_custom_stoploss_under_rel_1": 0.01,
      "sell_custom_stoploss_under_rsi_diff_1": 17.252,
      "sell_custom_under_profit_1": 0.084,
      "sell_custom_under_profit_2": 0.051,
      "sell_custom_under_profit_3": 0.095,
      "sell_custom_under_rsi_1": 49.6,
      "sell_custom_under_rsi_2": 60.1,
      "sell_custom_under_rsi_3": 51.1,
      "sell_dual_rsi_rsi_1h_4": 81.5,
      "sell_dual_rsi_rsi_4": 73.4,
      "sell_ema_relative_5": 0.02,
      "sell_rsi_1h_7": 82.2,
      "sell_rsi_bb_1": 64.4,
      "sell_rsi_bb_2": 80.5,
      "sell_rsi_diff_5": 15.903,
      "sell_rsi_main_3": 82.5,
      "sell_rsi_under_6": 83.9,
      "sell_trail_down_1": 0.185,
      "sell_trail_down_2": 0.136,
      "sell_trail_down_3": 0.04,
      "sell_trail_profit_max_1": 0.42,
      "sell_trail_profit_max_2": 0.25,
      "sell_trail_profit_max_3": 0.13,
      "sell_trail_profit_min_1": 0.115,
      "sell_trail_profit_min_2": 0.08,
      "sell_trail_profit_min_3": 0.074
    },
    "protection": {
      "lpp_lookback": 576,
      "lpp_pause": 300,
      "lpp_profit": -0.4,
      "lpp_trades": 3,
      "slg_limit": 1,
      "slg_lookback": 864,
      "slg_pause": 300
    },
    "roi": {
      "0": 0.103,
      "25": 0.065,
      "71": 0.039,
      "181": 0
    },
    "stoploss": {
      "stoploss": -0.205
    },
    "trailing": {
      "trailing_stop": true,
      "trailing_stop_positive": 0.026,
      "trailing_stop_positive_offset": 0.082,
      "trailing_only_offset_is_reached": true
    }
  },
  "ft_stratparam_v": 1,
  "export_time": "2025-06-07 05:17:22.070202+00:00"
}