{
  "strategy_name": "NFI5MOHO_WIP",
  "params": {
    "stoploss": {
      "stoploss": -0.99
    },
    "max_open_trades": {
      "max_open_trades": 5
    },
    "buy": {
      "base_nb_candles_buy": 24,
      "buy_bb20_close_bblowerband_4": 0.969,
      "buy_bb20_volume_4": 11.66,
      "buy_bb40_bbdelta_close_3": 0.012,
      "buy_bb40_closedelta_close_3": 0.01,
      "buy_bb40_tail_bbdelta_3": 0.169,
      "buy_bb_offset_10": 0.99,
      "buy_bb_offset_14": 1.0,
      "buy_bb_offset_18": 0.993,
      "buy_bb_offset_2": 0.999,
      "buy_bb_offset_5": 0.988,
      "buy_bb_offset_6": 0.986,
      "buy_bb_offset_9": 0.982,
      "buy_chop_min_19": 38.2,
      "buy_condition_10_enable": true,
      "buy_condition_11_enable": true,
      "buy_condition_12_enable": false,
      "buy_condition_13_enable": true,
      "buy_condition_14_enable": true,
      "buy_condition_15_enable": false,
      "buy_condition_16_enable": true,
      "buy_condition_17_enable": true,
      "buy_condition_18_enable": true,
      "buy_condition_19_enable": false,
      "buy_condition_1_enable": true,
      "buy_condition_20_enable": true,
      "buy_condition_21_enable": false,
      "buy_condition_2_enable": true,
      "buy_condition_3_enable": true,
      "buy_condition_4_enable": false,
      "buy_condition_5_enable": false,
      "buy_condition_6_enable": true,
      "buy_condition_7_enable": true,
      "buy_condition_8_enable": true,
      "buy_condition_9_enable": true,
      "buy_dip_threshold_1": 0.029,
      "buy_dip_threshold_10": 0.123,
      "buy_dip_threshold_11": 0.129,
      "buy_dip_threshold_12": 0.432,
      "buy_dip_threshold_2": 0.092,
      "buy_dip_threshold_3": 0.247,
      "buy_dip_threshold_4": 0.242,
      "buy_dip_threshold_5": 0.018,
      "buy_dip_threshold_6": 0.11,
      "buy_dip_threshold_7": 0.355,
      "buy_dip_threshold_8": 0.215,
      "buy_dip_threshold_9": 0.014,
      "buy_ema_open_mult_14": 0.011,
      "buy_ema_open_mult_15": 0.04,
      "buy_ema_open_mult_5": 0.02,
      "buy_ema_open_mult_6": 0.02,
      "buy_ema_open_mult_7": 0.033,
      "buy_ema_rel_15": 0.977,
      "buy_ema_rel_3": 0.978,
      "buy_ema_rel_5": 0.994,
      "buy_ema_rel_7": 0.991,
      "buy_ewo_12": 3.4,
      "buy_ewo_13": -8.2,
      "buy_ewo_16": 5.7,
      "buy_ewo_17": -17.9,
      "buy_ma_offset_10": 0.948,
      "buy_ma_offset_11": 0.962,
      "buy_ma_offset_12": 0.949,
      "buy_ma_offset_13": 0.973,
      "buy_ma_offset_14": 0.973,
      "buy_ma_offset_15": 0.959,
      "buy_ma_offset_16": 0.942,
      "buy_ma_offset_17": 0.972,
      "buy_ma_offset_9": 0.987,
      "buy_mfi_1": 34.2,
      "buy_mfi_11": 42.5,
      "buy_mfi_2": 50.1,
      "buy_mfi_9": 54.9,
      "buy_min_inc_1": 0.019,
      "buy_min_inc_11": 0.015,
      "buy_rsi_1": 32.6,
      "buy_rsi_11": 37.3,
      "buy_rsi_12": 34.6,
      "buy_rsi_15": 45.5,
      "buy_rsi_16": 42.4,
      "buy_rsi_18": 31.4,
      "buy_rsi_1h_10": 23.4,
      "buy_rsi_1h_20": 29.7,
      "buy_rsi_1h_21": 29.6,
      "buy_rsi_1h_diff_2": 47.8,
      "buy_rsi_1h_max_1": 75.3,
      "buy_rsi_1h_max_11": 72.5,
      "buy_rsi_1h_max_2": 83.7,
      "buy_rsi_1h_max_9": 87.6,
      "buy_rsi_1h_min_1": 32.6,
      "buy_rsi_1h_min_11": 40.8,
      "buy_rsi_1h_min_19": 59.4,
      "buy_rsi_1h_min_2": 37.8,
      "buy_rsi_1h_min_9": 34.0,
      "buy_rsi_20": 36.0,
      "buy_rsi_21": 24.7,
      "buy_rsi_7": 32.0,
      "buy_rsi_8": 39.9,
      "buy_tail_diff_8": 6.1,
      "buy_volume_10": 1.8,
      "buy_volume_12": 6.2,
      "buy_volume_13": 9.8,
      "buy_volume_14": 9.8,
      "buy_volume_15": 1.4,
      "buy_volume_16": 4.4,
      "buy_volume_17": 1.0,
      "buy_volume_18": 3.5,
      "buy_volume_2": 4.2,
      "buy_volume_20": 5.7,
      "buy_volume_21": 3.4,
      "buy_volume_7": 7.2,
      "buy_volume_8": 3.5,
      "buy_volume_9": 3.32,
      "ewo_high": 11.28,
      "ewo_low": -14.701,
      "fast_ewo": 14,
      "low_offset_ema": 0.97,
      "low_offset_kama": 0.965,
      "low_offset_sma": 0.916,
      "low_offset_t3": 0.9,
      "low_offset_trima": 0.918,
      "slow_ewo": 189
    },
    "sell": {
      "base_nb_candles_sell": 53,
      "high_offset_ema": 1.09,
      "high_offset_kama": 1.082,
      "high_offset_sma": 1.094,
      "high_offset_t3": 1.055,
      "high_offset_trima": 0.996,
      "sell_bb_relative_8": 1.098,
      "sell_condition_1_enable": true,
      "sell_condition_2_enable": true,
      "sell_condition_3_enable": true,
      "sell_condition_4_enable": true,
      "sell_condition_5_enable": true,
      "sell_condition_6_enable": false,
      "sell_condition_7_enable": false,
      "sell_condition_8_enable": true,
      "sell_custom_dec_profit_1": 0.049,
      "sell_custom_dec_profit_2": 0.106,
      "sell_custom_profit_0": 0.032,
      "sell_custom_profit_1": 0.014,
      "sell_custom_profit_2": 0.016,
      "sell_custom_profit_3": 0.209,
      "sell_custom_profit_4": 0.339,
      "sell_custom_profit_under_rel_1": 0.024,
      "sell_custom_profit_under_rsi_diff_1": 2.502,
      "sell_custom_rsi_0": 33.547,
      "sell_custom_rsi_1": 43.52,
      "sell_custom_rsi_2": 34.35,
      "sell_custom_rsi_3": 40.21,
      "sell_custom_rsi_4": 45.85,
      "sell_custom_stoploss_under_rel_1": 0.018,
      "sell_custom_stoploss_under_rsi_diff_1": 14.061,
      "sell_custom_under_profit_1": 0.046,
      "sell_custom_under_profit_2": 0.072,
      "sell_custom_under_profit_3": 0.03,
      "sell_custom_under_rsi_1": 44.0,
      "sell_custom_under_rsi_2": 50.8,
      "sell_custom_under_rsi_3": 57.2,
      "sell_dual_rsi_rsi_1h_4": 91.9,
      "sell_dual_rsi_rsi_4": 81.7,
      "sell_ema_relative_5": 0.03,
      "sell_rsi_1h_7": 82.0,
      "sell_rsi_bb_1": 73.4,
      "sell_rsi_bb_2": 81.6,
      "sell_rsi_diff_5": 0.065,
      "sell_rsi_main_3": 89.2,
      "sell_rsi_under_6": 88.6,
      "sell_trail_down_1": 0.089,
      "sell_trail_down_2": 0.128,
      "sell_trail_down_3": 0.04,
      "sell_trail_profit_max_1": 0.41,
      "sell_trail_profit_max_2": 0.23,
      "sell_trail_profit_max_3": 0.1,
      "sell_trail_profit_min_1": 0.239,
      "sell_trail_profit_min_2": 0.036,
      "sell_trail_profit_min_3": 0.092
    },
    "protection": {},
    "roi": {
      "0": 0.204,
      "30": 0.049,
      "80": 0.013,
      "170": 0
    },
    "trailing": {
      "trailing_stop": true,
      "trailing_stop_positive": 0.12,
      "trailing_stop_positive_offset": 0.219,
      "trailing_only_offset_is_reached": false
    }
  },
  "ft_stratparam_v": 1,
  "export_time": "2025-05-25 10:37:02.191372+00:00"
}